find_duplicate_contacts/__init__.py
find_duplicate_contacts/find_duplicate_contacts.py
find_duplicate_contacts-0.0.3.data/scripts/find_duplicate_contacts.py
find_duplicate_contacts-0.0.3.dist-info/LICENSE
find_duplicate_contacts-0.0.3.dist-info/METADATA
find_duplicate_contacts-0.0.3.dist-info/WHEEL
find_duplicate_contacts-0.0.3.dist-info/top_level.txt
find_duplicate_contacts-0.0.3.dist-info/RECORD
