Metadata-Version: 2.1
Name: find-duplicate-contacts
Version: 0.0.3
Summary: Find duplicate contacts in vCard files
Home-page: 
Author: Antonio J. Delgado
Author-email: "Antonio J. Delgado" <TXj6QGdwejbTD1iWAj2ws9pnV@susurrando.com>
License: 
Project-URL: Homepage, https://github.com/ajdelgado/find_duplicate_contacts
Keywords: vCard,contacts,duplicates
Classifier: License :: OSI Approved :: GNU General Public License v3 (GPLv3)
Classifier: Programming Language :: Python
Classifier: Programming Language :: Python :: 3
Requires-Python: >=3
License-File: LICENSE
Requires-Dist: vobject
Requires-Dist: click
Requires-Dist: click-config-file
Requires-Dist: deepdiff
